zq_config/__init__.py
zq_config/zq_configs.py
zq_config/backends/__init__.py
zq_config/backends/backend_registry.py
zq_config/backends/nacos.py
zq_config-0.1.5.dist-info/LICENSE.txt
zq_config-0.1.5.dist-info/METADATA
zq_config-0.1.5.dist-info/WHEEL
zq_config-0.1.5.dist-info/entry_points.txt
zq_config-0.1.5.dist-info/top_level.txt
zq_config-0.1.5.dist-info/RECORD
